server_templates/__init__.py
server_templates/client_requests.py
server_templates/url.py
server_templates/server_aiohttp/__init__.py
server_templates/server_aiohttp/main.py
server_templates/server_fastapi/__init__.py
server_templates/server_fastapi/main.py
server_templates-0.3.3.dist-info/LICENSE
server_templates-0.3.3.dist-info/METADATA
server_templates-0.3.3.dist-info/WHEEL
server_templates-0.3.3.dist-info/top_level.txt
server_templates-0.3.3.dist-info/RECORD
